lang_interface.py
lang_interface-0.1.0.dist-info/LICENSE
lang_interface-0.1.0.dist-info/METADATA
lang_interface-0.1.0.dist-info/WHEEL
lang_interface-0.1.0.dist-info/top_level.txt
lang_interface-0.1.0.dist-info/RECORD
