Metadata-Version: 2.1
Name: lang_interface
Version: 0.1.0
Summary: Integrate a Python programming interface with an LLM Assistant
Author-email: levy42 <vitali.levy@gmail.com>
Keywords: llm,assistant
License-File: LICENSE
Requires-Dist: tenacity >=7.0.0
